prassproject2/__init__.py
prassproject2/sample.py
prassproject2-0.0.1.dist-info/LICENSE.txt
prassproject2-0.0.1.dist-info/METADATA
prassproject2-0.0.1.dist-info/WHEEL
prassproject2-0.0.1.dist-info/top_level.txt
prassproject2-0.0.1.dist-info/RECORD
